nutorious/__init__.py
nutorious/cli/__init__.py
nutorious/config/__init__.py
nutorious/config/default.yml
nutorious/context/__init__.py
nutorious/journal/__init__.py
nutorious/model/__init__.py
nutorious/report/__init__.py
nutorious/report/base.py
nutorious/report/daily.py
nutorious/report/diff.py
nutorious/ui/__init__.py
nutorious/utils/collections.py
nutorious/utils/commons.py
nutorious-0.1.9.dist-info/LICENSE
nutorious-0.1.9.dist-info/METADATA
nutorious-0.1.9.dist-info/WHEEL
nutorious-0.1.9.dist-info/entry_points.txt
nutorious-0.1.9.dist-info/RECORD
