Metadata-Version: 2.1
Name: nutorious
Version: 0.1.9
Summary: 
Home-page: https://github.com/dzmitry-paulenka/nutorious
License: MIT
Author: Dzmitry Paulenka
Requires-Python: >=3.10,<4.0
Classifier: License :: OSI Approved :: MIT License
Classifier: Programming Language :: Python :: 3
Classifier: Programming Language :: Python :: 3.10
Classifier: Programming Language :: Python :: 3.11
Requires-Dist: attrs (>=23.1.0,<24.0.0)
Requires-Dist: cattrs (>=23.1.2,<24.0.0)
Requires-Dist: click (>=8.1.3,<9.0.0)
Requires-Dist: pydash (>=7.0.4,<8.0.0)
Requires-Dist: pyyaml (>=6.0,<7.0)
Requires-Dist: rich (>=13.4.1,<14.0.0)
Requires-Dist: watchfiles (>=0.19.0,<0.20.0)
Project-URL: Repository, https://github.com/dzmitry-paulenka/nutorious
